dot_parser.py
pydot.py
nxpydot-0.1.dist-info/DESCRIPTION.rst
nxpydot-0.1.dist-info/METADATA
nxpydot-0.1.dist-info/metadata.json
nxpydot-0.1.dist-info/RECORD
nxpydot-0.1.dist-info/top_level.txt
nxpydot-0.1.dist-info/WHEEL
