Metadata-Version: 2.0
Name: nxpydot
Version: 0.1
Summary: Wrapper round pydotplus to make it work with NetworkX
Home-page: http://github.com/pfmoore/nxpydot
Author: Paul Moore
Author-email: p.f.moore@gmail.com
License: MIT
Keywords: graphviz dot graphs visualization
Platform: UNKNOWN
Classifier: Development Status :: 3 - Alpha
Classifier: Intended Audience :: Science/Research
Classifier: Topic :: Scientific/Engineering :: Visualization
Classifier: Topic :: Software Development :: Libraries :: Python Modules
Classifier: License :: OSI Approved :: MIT License
Classifier: Programming Language :: Python :: 3
Classifier: Programming Language :: Python :: 3.3
Classifier: Programming Language :: Python :: 3.4
Requires-Dist: pydotplus
